LICENSE
README.md
setup.py
stoken/__init__.py
stoken/main.py
stoken.egg-info/PKG-INFO
stoken.egg-info/SOURCES.txt
stoken.egg-info/dependency_links.txt
stoken.egg-info/entry_points.txt
stoken.egg-info/requires.txt
stoken.egg-info/top_level.txt