Metadata-Version: 2.1
Name: stoken
Version: 0.2.2
Summary: A code desensitization tool, which can substitute tokens (and other sensitive information) in your code.
Home-page: https://github.com/laorange/stoken
Author: laorange
Author-email: laorange6666@gmail.com
License: AGPL-3.0
Project-URL: Bug Tracker, https://github.com/laorange/stoken/issues
Project-URL: Source Code, https://github.com/laorange/stoken
Keywords: git,data desensitization,replace token
Platform: any
License-File: LICENSE
